TrboDataSvc/__init__.py
TrboDataSvc/ars.py
TrboDataSvc/battery.py
TrboDataSvc/jobticket.py
TrboDataSvc/lrrp.py
TrboDataSvc/tms.py
TrboDataSvc/util.py
TrboDataSvc-0.0.8.dist-info/LICENSE.md
TrboDataSvc-0.0.8.dist-info/METADATA
TrboDataSvc-0.0.8.dist-info/WHEEL
TrboDataSvc-0.0.8.dist-info/top_level.txt
TrboDataSvc-0.0.8.dist-info/RECORD
