Metadata-Version: 2.1
Name: TrboDataSvc
Version: 0.0.8
Summary: A collection of libraries to handle communication and interpretation of MotoTRBO Data Services (ARS, TMS, LRRP, Job Tickets, etc)
Home-page: https://git.natnat.xyz/natalie/TrboDataSvc
Author: Natalie
Author-email: natalie@natnat.xyz
License: UNKNOWN
Project-URL: Bug Tracker, https://git.natnat.xyz/natalie/TrboDataSvc/-/issues
Platform: UNKNOWN
Classifier: Programming Language :: Python :: 3
Classifier: License :: OSI Approved :: MIT License
Classifier: Operating System :: OS Independent
Requires-Python: >=3.6
License-File: LICENSE.md
